prefect_dask/__init__.py
prefect_dask/_version.py
prefect_dask/client.py
prefect_dask/py.typed
prefect_dask/task_runners.py
prefect_dask/utils.py
prefect_dask-0.3.6.dist-info/licenses/LICENSE
prefect_dask-0.3.6.dist-info/METADATA
prefect_dask-0.3.6.dist-info/WHEEL
prefect_dask-0.3.6.dist-info/entry_points.txt
prefect_dask-0.3.6.dist-info/top_level.txt
prefect_dask-0.3.6.dist-info/RECORD
